lib_test/__init__.py
lib_test/command_line.py
lib_test/hello.py
lib_test/setup.py
lib_test/sub_dir/__init__.py
lib_test/sub_dir/bye.py
lib_test_98765-0.0.2.dist-info/METADATA
lib_test_98765-0.0.2.dist-info/WHEEL
lib_test_98765-0.0.2.dist-info/entry_points.txt
lib_test_98765-0.0.2.dist-info/top_level.txt
lib_test_98765-0.0.2.dist-info/RECORD
