Metadata-Version: 2.1
Name: lib-test-98765
Version: 0.0.2
Summary: UNKNOWN
Home-page: UNKNOWN
License: UNKNOWN
Platform: UNKNOWN
Requires-Dist: python-dotenv (==1.0.0)
